measurement/__init__.py
measurement/measurements.py
measurement/plugins/__init__.py
measurement/plugins/download_speed/__init__.py
measurement/plugins/download_speed/measurements.py
measurement/plugins/download_speed/results.py
measurement/plugins/download_speed/results_py3.py
measurement/plugins/download_speed/tests/__init__.py
measurement/plugins/download_speed/tests/test_measurements.py
measurement/plugins/ip_route/measurements.py
measurement/plugins/ip_route/results.py
measurement/plugins/ip_route/results_py3.py
measurement/plugins/ip_route/tests/__init__.py
measurement/plugins/ip_route/tests/test_measurements.py
measurement/plugins/latency/__init__.py
measurement/plugins/latency/measurements.py
measurement/plugins/latency/results.py
measurement/plugins/latency/results_py3.py
measurement/plugins/latency/tests/__init__.py
measurement/plugins/latency/tests/test_measurements.py
measurement/plugins/netflix_fast/__init__.py
measurement/plugins/netflix_fast/measurements.py
measurement/plugins/netflix_fast/results.py
measurement/plugins/netflix_fast/results_py3.py
measurement/plugins/netflix_fast/tests/__init__.py
measurement/plugins/netflix_fast/tests/test_measurements.py
measurement/plugins/speedtestdotnet/__init__.py
measurement/plugins/speedtestdotnet/measurements.py
measurement/plugins/speedtestdotnet/results.py
measurement/plugins/speedtestdotnet/results_py3.py
measurement/plugins/speedtestdotnet/tests/__init__.py
measurement/plugins/speedtestdotnet/tests/test_measurements.py
measurement/plugins/youtube/__init__.py
measurement/plugins/youtube/measurements.py
measurement/plugins/youtube/results.py
measurement/plugins/youtube/results_py3.py
measurement/plugins/youtube/tests/__init__.py
measurement/plugins/youtube/tests/test_measurements.py
measurement/results.py
measurement/results_py3.py
measurement/units.py
honestybox_measurement-1.1.0.dist-info/LICENSE.txt
honestybox_measurement-1.1.0.dist-info/WHEEL
honestybox_measurement-1.1.0.dist-info/METADATA
honestybox_measurement-1.1.0.dist-info/RECORD
