Metadata-Version: 2.1
Name: honestybox-measurement
Version: 1.1.0
Summary: A framework for measuring things and producing structured results.
Home-page: https://github.com/honesty-box/honestybox-measurement/
Author: James Stewart
Author-email: james@amorphitec.io
Maintainer: Honesty Box
Maintainer-email: engineering@honestybox.com.au
Requires-Python: >=3.5,<4
Classifier: Programming Language :: Python :: 3
Classifier: Programming Language :: Python :: 3.5
Classifier: Programming Language :: Python :: 3.6
Classifier: Programming Language :: Python :: 3.7
Classifier: Programming Language :: Python :: 3.8
Requires-Dist: dataclasses (>=0.6.0,<0.7.0); python_version >= "3.6.0" and python_version < "4.0.0"
Requires-Dist: requests (>=2.23.0,<3.0.0)
Requires-Dist: scapy (>=2.4.4-rc.2,<3.0.0)
Requires-Dist: six (>=1.12,<2.0)
Requires-Dist: speedtest-cli (>=2.1,<3.0)
Requires-Dist: statistics (>=1.0.3,<2.0.0)
Requires-Dist: validators (>=0.13.0,<0.14.0)
Requires-Dist: youtube_dl (>=2020.6.16,<2021.0.0)
Project-URL: Repository, https://github.com/honesty-box/honestybox-measurement/
